{
  "id": "BE-WNA-andenne",
  "name": "Andenne (Belgium)",
  "type": [
    "city"
  ],
  "parent": "BE-WNA",
  "codes": {
    "wikidata": "Q333466"
  },
  "region": [
    "Europe",
    "Western Europe",
    "European Union"
  ],
  "aspect_ratio": "2:3",
  "colors": [
    {
      "color": "yellow",
      "symbolism": "the upper band"
    },
    {
      "color": "black",
      "symbolism": "the lower band"
    }
  ],
  "description": "Two horizontal bands of gold and black.",
  "history": "The flag of Andenne derives from the municipal coat of arms.",
  "sources": [
    "https://commons.wikimedia.org/wiki/File:Flag_of_Andenne.svg",
    "https://www.wikidata.org/wiki/Q333466"
  ],
  "features": [
    {
      "type": "horizontal-stripes",
      "stripes": [
        "yellow",
        "black"
      ],
      "count": 2
    }
  ]
}
