{
  "id": "CL-AP",
  "name": "Arica y Parinacota Region (Chile)",
  "type": [
    "subdivision"
  ],
  "parent": "CL",
  "codes": {
    "iso_3166_2": "CL-AP",
    "wikidata": "Q2109"
  },
  "region": [
    "Americas",
    "South America",
    "Latin America"
  ],
  "aspect_ratio": "2:3",
  "colors": [
    {
      "color": "white"
    }
  ],
  "description": "White field bearing the logo of the Arica y Parinacota Regional Government.",
  "sources": [
    "https://www.wikidata.org/wiki/Q2109",
    "https://commons.wikimedia.org/wiki/Special:FilePath/Flag%20of%20Arica%20y%20Parinacota%2C%20Chile.svg"
  ],
  "features": [
    {
      "type": "solid",
      "color": "white"
    },
    {
      "type": "complex"
    }
  ]
}