{
  "id": "CL-NB",
  "name": "Ñuble Region (Chile)",
  "type": [
    "subdivision"
  ],
  "parent": "CL",
  "codes": {
    "iso_3166_2": "CL-NB",
    "wikidata": "Q24076693"
  },
  "region": [
    "Americas",
    "South America",
    "Latin America"
  ],
  "aspect_ratio": "2:3",
  "colors": [
    {
      "color": "white"
    }
  ],
  "description": "White field with the crowned coat of arms of the Ñuble Region.",
  "sources": [
    "https://www.wikidata.org/wiki/Q24076693",
    "https://commons.wikimedia.org/wiki/Special:FilePath/Flag%20of%20%C3%91uble%20Region%2C%20Chile.svg"
  ],
  "features": [
    {
      "type": "solid",
      "color": "white"
    },
    {
      "type": "coat-of-arms",
      "position": "center"
    }
  ]
}