{
  "id": "NL-NB-valkenswaard",
  "name": "Valkenswaard (Netherlands)",
  "type": [
    "city"
  ],
  "parent": "NL-NB",
  "codes": {
    "wikidata": "Q9873"
  },
  "region": [
    "Europe",
    "Western Europe",
    "European Union"
  ],
  "aspect_ratio": "2:3",
  "colors": [
    {
      "color": "light-blue",
      "symbolism": "upper band"
    },
    {
      "color": "yellow",
      "symbolism": "lower band"
    }
  ],
  "description": "Light blue over yellow.",
  "history": "Flag of the municipality of Valkenswaard in the province of North Brabant.",
  "sources": [
    "https://nl.wikipedia.org/wiki/Vlag_van_Valkenswaard",
    "https://commons.wikimedia.org/wiki/File:Flag_of_Valkenswaard.svg"
  ],
  "features": [
    {
      "type": "horizontal-stripes",
      "stripes": [
        "light-blue",
        "yellow"
      ],
      "count": 2
    }
  ]
}
