{
  "id": "PE-MDD",
  "name": "Madre de Dios Department (Peru)",
  "type": [
    "subdivision"
  ],
  "parent": "PE",
  "codes": {
    "iso_3166_2": "PE-MDD",
    "wikidata": "Q210896"
  },
  "region": [
    "Americas",
    "South America",
    "Latin America",
    "Hispanic"
  ],
  "aspect_ratio": "2:3",
  "colors": [
    {
      "color": "green"
    },
    {
      "color": "yellow"
    }
  ],
  "description": "A green field crossed by a diagonal yellow band.",
  "history": "The flag of the Madre de Dios Department of Peru.",
  "variant": [
    "civil",
    "state"
  ],
  "sources": [
    "https://www.wikidata.org/wiki/Q210896",
    "https://commons.wikimedia.org/wiki/Category:Flags_of_Peru"
  ],
  "features": [
    {
      "type": "solid",
      "color": "green"
    },
    {
      "type": "diagonal-stripes",
      "stripes": [
        "green",
        "yellow",
        "green"
      ],
      "count": 3
    }
  ]
}
