{
  "id": "SK-BL-bratislava",
  "name": "Bratislava (Slovakia)",
  "type": ["city"],
  "parent": "SK-BL",
  "codes": {
    "wikidata": "Q1780"
  },
  "region": [
    "Europe",
    "Eastern Europe",
    "European Union",
    "Slavic"
  ],
  "shape": "swallowtail",
  "aspect_ratio": "2:3",
  "colors": [
    { "color": "white", "symbolism": "the upper stripe; the silver (argent) of the city's arms" },
    { "color": "red", "symbolism": "the lower stripe and the city's heraldic colour" }
  ],
  "description": "Two equal horizontal stripes, an upper white and a lower red, capped with a swallowtail cut into the fly.",
  "history": "Bratislava is the capital and largest city of Slovakia. The white-over-red flag takes its colours from the city's arms — a silver three-towered fortification on a red field — a design dating to the medieval period. The arms are a separate municipal symbol and do not appear on the flag.",
  "periods": [
    {
      "start": "1991~"
    }
  ],
  "sources": [
    "https://en.wikipedia.org/wiki/Bratislava",
    "https://bratislava.sk/en/city-of-bratislava/city-administration/the-citys-visual-identity/symbols-of-bratislava"
  ],
  "features": [
    {
      "type": "horizontal-stripes",
      "stripes": ["white", "red"],
      "count": 2
    }
  ]
}
